mesh/__init__.py
mesh/client.py
mesh_python-0.4.dist-info/LICENSE
mesh_python-0.4.dist-info/METADATA
mesh_python-0.4.dist-info/WHEEL
mesh_python-0.4.dist-info/top_level.txt
mesh_python-0.4.dist-info/RECORD
